HTS_doseresponse/__init__.py
HTS_doseresponse/ht_curve_fitting.py
HTS_doseresponse/data/__init__.py
HTS_doseresponse/data/example_data.csv
HTS_doseresponse-0.0.5.dist-info/LICENSE
HTS_doseresponse-0.0.5.dist-info/METADATA
HTS_doseresponse-0.0.5.dist-info/WHEEL
HTS_doseresponse-0.0.5.dist-info/top_level.txt
HTS_doseresponse-0.0.5.dist-info/RECORD
