Metadata-Version: 2.1
Name: HTS_doseresponse
Version: 0.0.5
Summary: Dose Response Curve Fitting
Author-email: Scott McPhee <sahmcphee@gmail.com>
License: MIT License
Project-URL: Homepage, https://github.com/samcphee/HTS_doseresponse
Project-URL: Issues, https://github.com/samcphee/HTS_doseresponse/issues
Keywords: IC50,biochemistry,pharmacology
Classifier: License :: OSI Approved :: MIT License
Classifier: Programming Language :: Python
Classifier: Programming Language :: Python :: 3
Classifier: Operating System :: OS Independent
Requires-Python: >=3.10.12
License-File: LICENSE
Requires-Dist: pandas >=1.5.3
Requires-Dist: seaborn >=0.13.1
Requires-Dist: scipy >=1.11.4
Requires-Dist: tomli ; python_version < "3.11"
Provides-Extra: dev
Requires-Dist: pip-tools ; extra == 'dev'
Requires-Dist: pytest ; extra == 'dev'
